LICENSE
README.md
setup.py
aidedkit/__init__.py
aidedkit/lib.py
aidedkit/mavlink.py
aidedkit/util.py
aidedkit.egg-info/PKG-INFO
aidedkit.egg-info/SOURCES.txt
aidedkit.egg-info/dependency_links.txt
aidedkit.egg-info/requires.txt
aidedkit.egg-info/top_level.txt
aidedkit.egg-info/zip-safe
aidedkit/test/__init__.py
aidedkit/test/sitl/__init__.py
aidedkit/test/sitl/test_110.py
aidedkit/test/sitl/test_115.py
aidedkit/test/sitl/test_12.py
aidedkit/test/sitl/test_capability_and_version.py
aidedkit/test/sitl/test_channels.py
aidedkit/test/sitl/test_earlyattrs.py
aidedkit/test/sitl/test_errprinter.py
aidedkit/test/sitl/test_goto.py
aidedkit/test/sitl/test_locations.py
aidedkit/test/sitl/test_mavlink.py
aidedkit/test/sitl/test_mode_settings.py
aidedkit/test/sitl/test_modeavailable.py
aidedkit/test/sitl/test_parameters.py
aidedkit/test/sitl/test_reboot.py
aidedkit/test/sitl/test_sensor_calibration.py
aidedkit/test/sitl/test_simpledemo.py
aidedkit/test/sitl/test_state.py
aidedkit/test/sitl/test_timeout.py
aidedkit/test/sitl/test_vehicleclass.py
aidedkit/test/sitl/test_waypoints.py
aidedkit/test/unit/__init__.py
aidedkit/test/unit/test_api.py