Metadata-Version: 2.1
Name: aidedkit
Version: 1.0.0
Summary: Developer Tools for Drones.
Home-page: https://github.com/dronekit/dronekit-python
Author: 3D Robotics
Author-email: tim@3drobotics.com, kevinh@geeksville.com
License: apache
Classifier: Development Status :: 5 - Production/Stable
Classifier: Environment :: Console
Classifier: Intended Audience :: Science/Research
Classifier: License :: OSI Approved :: Apache Software License
Classifier: Operating System :: OS Independent
Classifier: Programming Language :: Python :: 2.7
Classifier: Programming Language :: Python :: 3
Classifier: Topic :: Scientific/Engineering
License-File: LICENSE
